ding/__init__.py
ding/ding.py
ding_ding-2.0.0.dist-info/DESCRIPTION.rst
ding_ding-2.0.0.dist-info/METADATA
ding_ding-2.0.0.dist-info/RECORD
ding_ding-2.0.0.dist-info/WHEEL
ding_ding-2.0.0.dist-info/entry_points.txt
ding_ding-2.0.0.dist-info/metadata.json
ding_ding-2.0.0.dist-info/top_level.txt
