Metadata-Version: 2.0
Name: ding-ding
Version: 2.0.0
Summary: Quick organisation via the commandline
Home-page: https://github.com/liviu-/ding
Author: UNKNOWN
Author-email: UNKNOWN
License: MIT
Platform: UNKNOWN
